weathermcpqhzy/__init__.py
weathermcpqhzy/__main__.py
weathermcpqhzy/py.typed
weathermcpqhzy/weathermcpqhzy.py
weathermcpqhzy-0.1.0.dist-info/METADATA
weathermcpqhzy-0.1.0.dist-info/WHEEL
weathermcpqhzy-0.1.0.dist-info/entry_points.txt
weathermcpqhzy-0.1.0.dist-info/RECORD
